{
  "data": {
    "article": {},
    "attachments": {
      "media_keys": [
        "3_1840367177473589248"
      ],
      "media_source_tweet_id": [
        "1840367181688918380"
      ]
    },
    "author_id": "1639996371879985157",
    "conversation_id": "1840725031774756919",
    "created_at": "2024-09-30T12:07:01.000Z",
    "edit_controls": {
      "editable_until": "2024-09-30T13:07:01.000Z",
      "edits_remaining": 5,
      "is_edit_eligible": false
    },
    "edit_history_tweet_ids": [
      "1840725031774756919"
    ],
    "entities": {
      "mentions": [
        {
          "end": 13,
          "id": "1226850561057624064",
          "start": 3,
          "username": "hatadanna"
        }
      ],
      "urls": [
        {
          "display_url": "pic.x.com/ysa1659dtc",
          "end": 65,
          "expanded_url": "https://twitter.com/hatadanna/status/1840367181688918380/photo/1",
          "media_key": "3_1840367177473589248",
          "start": 42,
          "url": "https://t.co/ysA1659dTC"
        }
      ]
    },
    "geo": {},
    "id": "1840725031774756919",
    "lang": "zh",
    "possibly_sensitive": true,
    "public_metrics": {
      "bookmark_count": 0,
      "impression_count": 0,
      "like_count": 0,
      "quote_count": 0,
      "reply_count": 0,
      "retweet_count": 50
    },
    "referenced_tweets": [
      {
        "id": "1840367181688918380",
        "type": "retweeted"
      }
    ],
    "reply_settings": "everyone",
    "text": "RT @hatadanna: 时间见证了每个人的幸福，也目睹了不欢而散的每个夜晚。 https://t.co/ysA1659dTC"
  },
  "includes": {
    "media": [
      {
        "height": 637,
        "media_key": "3_1840367177473589248",
        "public_metrics": {},
        "type": "photo",
        "url": "https://pbs.twimg.com/media/GYpMMn2aAAANuTp.jpg",
        "width": 1252
      }
    ],
    "tweets": [
      {
        "article": {},
        "attachments": {
          "media_keys": [
            "3_1840367177473589248"
          ],
          "media_source_tweet_id": [
            "1840367181688918380"
          ]
        },
        "author_id": "1639996371879985157",
        "conversation_id": "1840725031774756919",
        "created_at": "2024-09-30T12:07:01.000Z",
        "edit_controls": {
          "editable_until": "2024-09-30T13:07:01.000Z",
          "edits_remaining": 5,
          "is_edit_eligible": false
        },
        "edit_history_tweet_ids": [
          "1840725031774756919"
        ],
        "entities": {
          "mentions": [
            {
              "end": 13,
              "id": "1226850561057624064",
              "start": 3,
              "username": "hatadanna"
            }
          ],
          "urls": [
            {
              "display_url": "pic.x.com/ysa1659dtc",
              "end": 65,
              "expanded_url": "https://twitter.com/hatadanna/status/1840367181688918380/photo/1",
              "media_key": "3_1840367177473589248",
              "start": 42,
              "url": "https://t.co/ysA1659dTC"
            }
          ]
        },
        "geo": {},
        "id": "1840725031774756919",
        "lang": "zh",
        "possibly_sensitive": true,
        "public_metrics": {
          "bookmark_count": 0,
          "impression_count": 0,
          "like_count": 0,
          "quote_count": 0,
          "reply_count": 0,
          "retweet_count": 50
        },
        "referenced_tweets": [
          {
            "id": "1840367181688918380",
            "type": "retweeted"
          }
        ],
        "reply_settings": "everyone",
        "text": "RT @hatadanna: 时间见证了每个人的幸福，也目睹了不欢而散的每个夜晚。 https://t.co/ysA1659dTC"
      },
      {
        "article": {},
        "attachments": {
          "media_keys": [
            "3_1840367177473589248"
          ]
        },
        "author_id": "1226850561057624064",
        "conversation_id": "1840367181688918380",
        "created_at": "2024-09-29T12:25:03.000Z",
        "edit_controls": {
          "editable_until": "2024-09-29T13:25:03.000Z",
          "edits_remaining": 5,
          "is_edit_eligible": true
        },
        "edit_history_tweet_ids": [
          "1840367181688918380"
        ],
        "entities": {
          "urls": [
            {
              "display_url": "pic.x.com/ysa1659dtc",
              "end": 50,
              "expanded_url": "https://twitter.com/hatadanna/status/1840367181688918380/photo/1",
              "media_key": "3_1840367177473589248",
              "start": 27,
              "url": "https://t.co/ysA1659dTC"
            }
          ]
        },
        "geo": {},
        "id": "1840367181688918380",
        "lang": "zh",
        "possibly_sensitive": false,
        "public_metrics": {
          "bookmark_count": 30,
          "impression_count": 16597,
          "like_count": 408,
          "quote_count": 2,
          "reply_count": 1,
          "retweet_count": 50
        },
        "reply_settings": "everyone",
        "text": "时间见证了每个人的幸福，也目睹了不欢而散的每个夜晚。 https://t.co/ysA1659dTC"
      }
    ],
    "users": [
      {
        "created_at": "2023-03-26T14:23:40.000Z",
        "description": "狂暴照料@lan_shang32900中，千万要早日康复🥺    一朵老鈴蘭，幸福原生家庭养出来的INFP，一半神经一半健全的游离态",
        "entities": {
          "description": {
            "mentions": [
              {
                "end": 19,
                "start": 4,
                "username": "lan_shang32900"
              }
            ]
          }
        },
        "id": "1639996371879985157",
        "location": "Laniakea Supercluster ",
        "name": "*⁂汐渋⁂*.･ﾟﾟ",
        "pinned_tweet_id": "1835705937086333243",
        "profile_image_url": "https://pbs.twimg.com/profile_images/1745757156874534912/z8Gowc7Y_normal.jpg",
        "protected": false,
        "public_metrics": {
          "followers_count": 355,
          "following_count": 457,
          "like_count": 21474,
          "listed_count": 2,
          "tweet_count": 8297
        },
        "username": "SupernovaLLan",
        "verified": false
      },
      {
        "created_at": "2020-02-10T12:49:13.000Z",
        "description": "梗图bot | 日常分享 | 爱大家 | Et Omnia Vanitas.",
        "entities": {
          "url": {
            "urls": [
              {
                "display_url": "bento.me/hatadanna",
                "end": 23,
                "expanded_url": "http://bento.me/hatadanna",
                "start": 0,
                "url": "https://t.co/y4ubULnlbw"
              }
            ]
          }
        },
        "id": "1226850561057624064",
        "location": "梦里",
        "name": "旗田安奈🍵",
        "pinned_tweet_id": "1840377624906047814",
        "profile_image_url": "https://pbs.twimg.com/profile_images/1691374845140082688/f2RPoY8q_normal.jpg",
        "protected": false,
        "public_metrics": {
          "followers_count": 19714,
          "following_count": 3248,
          "like_count": 10654,
          "listed_count": 89,
          "tweet_count": 6590
        },
        "url": "https://t.co/y4ubULnlbw",
        "username": "hatadanna",
        "verified": true
      }
    ]
  }
}