{
  "data": {
    "article": {},
    "attachments": {},
    "author_id": "1639996371879985157",
    "conversation_id": "1928801145494839696",
    "created_at": "2025-05-31T13:11:09.000Z",
    "edit_controls": {
      "editable_until": "2025-05-31T14:11:09.000Z",
      "edits_remaining": 5,
      "is_edit_eligible": false
    },
    "edit_history_tweet_ids": [
      "1928801425049428226"
    ],
    "entities": {
      "mentions": [
        {
          "end": 11,
          "id": "1650760116918943744",
          "start": 0,
          "username": "minamitwo2"
        }
      ]
    },
    "geo": {},
    "id": "1928801425049428226",
    "in_reply_to_user_id": "1650760116918943744",
    "lang": "zh",
    "note_tweet": {
      "entities": {}
    },
    "possibly_sensitive": false,
    "public_metrics": {
      "bookmark_count": 0,
      "impression_count": 0,
      "like_count": 0,
      "quote_count": 0,
      "reply_count": 0,
      "retweet_count": 0
    },
    "referenced_tweets": [
      {
        "id": "1928801145494839696",
        "type": "replied_to"
      }
    ],
    "reply_settings": "everyone",
    "text": "@minamitwo2 帅啊😻"
  },
  "includes": {
    "media": [
      {
        "height": 1451,
        "media_key": "3_1928801142076747778",
        "public_metrics": {},
        "type": "photo",
        "url": "https://pbs.twimg.com/media/GsR6a2PaMAI5dL4.jpg",
        "width": 2048
      }
    ],
    "tweets": [
      {
        "article": {},
        "attachments": {},
        "author_id": "1639996371879985157",
        "conversation_id": "1928801145494839696",
        "created_at": "2025-05-31T13:11:09.000Z",
        "edit_controls": {
          "editable_until": "2025-05-31T14:11:09.000Z",
          "edits_remaining": 5,
          "is_edit_eligible": false
        },
        "edit_history_tweet_ids": [
          "1928801425049428226"
        ],
        "entities": {
          "mentions": [
            {
              "end": 11,
              "id": "1650760116918943744",
              "start": 0,
              "username": "minamitwo2"
            }
          ]
        },
        "geo": {},
        "id": "1928801425049428226",
        "in_reply_to_user_id": "1650760116918943744",
        "lang": "zh",
        "note_tweet": {
          "entities": {}
        },
        "possibly_sensitive": false,
        "public_metrics": {
          "bookmark_count": 0,
          "impression_count": 0,
          "like_count": 0,
          "quote_count": 0,
          "reply_count": 0,
          "retweet_count": 0
        },
        "referenced_tweets": [
          {
            "id": "1928801145494839696",
            "type": "replied_to"
          }
        ],
        "reply_settings": "everyone",
        "text": "@minamitwo2 帅啊😻"
      },
      {
        "article": {},
        "attachments": {
          "media_keys": [
            "3_1928801142076747778"
          ]
        },
        "author_id": "1650760116918943744",
        "conversation_id": "1928801145494839696",
        "created_at": "2025-05-31T13:10:03.000Z",
        "edit_controls": {
          "editable_until": "2025-05-31T14:10:03.000Z",
          "edits_remaining": 5,
          "is_edit_eligible": true
        },
        "edit_history_tweet_ids": [
          "1928801145494839696"
        ],
        "entities": {
          "urls": [
            {
              "display_url": "pic.x.com/skz9eKhPY4",
              "end": 23,
              "expanded_url": "https://x.com/minamitwo2/status/1928801145494839696/photo/1",
              "media_key": "3_1928801142076747778",
              "start": 0,
              "url": "https://t.co/skz9eKhPY4"
            }
          ]
        },
        "geo": {},
        "id": "1928801145494839696",
        "lang": "zxx",
        "note_tweet": {
          "entities": {}
        },
        "possibly_sensitive": false,
        "public_metrics": {
          "bookmark_count": 0,
          "impression_count": 5,
          "like_count": 4,
          "quote_count": 0,
          "reply_count": 1,
          "retweet_count": 0
        },
        "reply_settings": "everyone",
        "text": "https://t.co/skz9eKhPY4"
      }
    ],
    "users": [
      {
        "created_at": "2023-03-26T14:23:40.000Z",
        "description": "",
        "id": "1639996371879985157",
        "location": "Laniakea Supercluster ",
        "name": "*⁂汐渋鈴蘭⁂*.･ﾟﾟ",
        "pinned_tweet_id": "1835705937086333243",
        "profile_image_url": "https://pbs.twimg.com/profile_images/1745757156874534912/z8Gowc7Y_normal.jpg",
        "protected": false,
        "public_metrics": {
          "followers_count": 338,
          "following_count": 548,
          "like_count": 24612,
          "listed_count": 2,
          "media_count": 1055,
          "tweet_count": 9665
        },
        "username": "SupernovaLLan",
        "verified": false
      },
      {
        "created_at": "2023-04-25T07:14:30.000Z",
        "description": "我是小南  喜欢二次元 小动物 做手工",
        "entities": {
          "url": {
            "urls": [
              {
                "display_url": "xnmoe.com",
                "end": 23,
                "expanded_url": "http://xnmoe.com",
                "start": 0,
                "url": "https://t.co/OXuM4vbTaK"
              }
            ]
          }
        },
        "id": "1650760116918943744",
        "location": "鼠鼠星",
        "name": "🍀🌵",
        "pinned_tweet_id": "1913006347765137642",
        "profile_image_url": "https://pbs.twimg.com/profile_images/1924863650831249408/pJ3xtRVg_normal.jpg",
        "protected": false,
        "public_metrics": {
          "followers_count": 3694,
          "following_count": 949,
          "like_count": 56920,
          "listed_count": 6,
          "media_count": 537,
          "tweet_count": 11492
        },
        "url": "https://t.co/OXuM4vbTaK",
        "username": "minamitwo2",
        "verified": false
      }
    ]
  }
}